oletools/LICENSE.txt
oletools/README.html
oletools/README.rst
oletools/__init__.py
oletools/crypto.py
oletools/ezhexviewer.py
oletools/ftguess.py
oletools/mraptor.py
oletools/mraptor3.py
oletools/mraptor_milter.py
oletools/msodde.py
oletools/olebrowse.py
oletools/oledir.py
oletools/oleform.py
oletools/oleid.py
oletools/olemap.py
oletools/olemeta.py
oletools/oleobj.py
oletools/oletimes.py
oletools/olevba.py
oletools/olevba3.py
oletools/ooxml.py
oletools/ppt_parser.py
oletools/ppt_record_parser.py
oletools/pyxswf.py
oletools/record_base.py
oletools/rtfobj.py
oletools/xls_parser.py
oletools/common/__init__.py
oletools/common/clsid.py
oletools/common/codepages.py
oletools/common/errors.py
oletools/common/io_encoding.py
oletools/common/log_helper/__init__.py
oletools/common/log_helper/_json_formatter.py
oletools/common/log_helper/_logger_adapter.py
oletools/common/log_helper/_root_logger_wrapper.py
oletools/common/log_helper/log_helper.py
oletools/doc/Changelog.md
oletools/doc/Contribute.html
oletools/doc/Contribute.md
oletools/doc/Home.html
oletools/doc/Home.md
oletools/doc/Install.html
oletools/doc/Install.md
oletools/doc/License.html
oletools/doc/License.md
oletools/doc/formats_vs_techniques.md
oletools/doc/mraptor.html
oletools/doc/mraptor.md
oletools/doc/mraptor1.png
oletools/doc/msodde.html
oletools/doc/msodde.md
oletools/doc/olebrowse.html
oletools/doc/olebrowse.md
oletools/doc/olebrowse1_menu.png
oletools/doc/olebrowse2_stream.png
oletools/doc/olebrowse3_hexview.png
oletools/doc/oledir.html
oletools/doc/oledir.md
oletools/doc/oledir.png
oletools/doc/oleid.html
oletools/doc/oleid.md
oletools/doc/olemap.html
oletools/doc/olemap.md
oletools/doc/olemap1.png
oletools/doc/olemap2.png
oletools/doc/olemeta.html
oletools/doc/olemeta.md
oletools/doc/olemeta1.png
oletools/doc/oleobj.html
oletools/doc/oleobj.md
oletools/doc/oletimes.html
oletools/doc/oletimes.md
oletools/doc/olevba.html
oletools/doc/olevba.md
oletools/doc/pyxswf.html
oletools/doc/pyxswf.md
oletools-0.60.1.dist-info/LICENSE.md
oletools-0.60.1.dist-info/METADATA
oletools-0.60.1.dist-info/WHEEL
oletools-0.60.1.dist-info/entry_points.txt
oletools-0.60.1.dist-info/top_level.txt
oletools-0.60.1.dist-info/RECORD
