Metadata-Version: 2.1
Name: oletools
Version: 0.60.1
Summary: Python tools to analyze security characteristics of MS Office and OLE files (also called Structured Storage, Compound File Binary Format or Compound Document File Format), for Malware Analysis and Incident Response #DFIR
Home-page: http://www.decalage.info/python/oletools
Author: Philippe Lagadec
Author-email: nospam@decalage.info
License: BSD
Download-URL: https://github.com/decalage2/oletools/releases
Platform: UNKNOWN
Classifier: Development Status :: 4 - Beta
Classifier: Intended Audience :: Developers
Classifier: Intended Audience :: Information Technology
Classifier: Intended Audience :: Science/Research
Classifier: Intended Audience :: System Administrators
Classifier: License :: OSI Approved :: BSD License
Classifier: Natural Language :: English
Classifier: Operating System :: OS Independent
Classifier: Programming Language :: Python
Classifier: Programming Language :: Python :: 2
Classifier: Programming Language :: Python :: 2.7
Classifier: Programming Language :: Python :: 3
Classifier: Programming Language :: Python :: 3.4
Classifier: Programming Language :: Python :: 3.5
Classifier: Programming Language :: Python :: 3.6
Classifier: Programming Language :: Python :: 3.7
Classifier: Programming Language :: Python :: 3.8
Classifier: Programming Language :: Python :: 3.9
Classifier: Topic :: Security
Classifier: Topic :: Software Development :: Libraries :: Python Modules
Provides-Extra: full
